NexR_dqc/PreProcess.py
NexR_dqc/__init__.py
NexR_dqc-0.4.0.dist-info/LICENSE
NexR_dqc-0.4.0.dist-info/METADATA
NexR_dqc-0.4.0.dist-info/WHEEL
NexR_dqc-0.4.0.dist-info/top_level.txt
NexR_dqc-0.4.0.dist-info/RECORD
