Metadata-Version: 2.1
Name: NexR-dqc
Version: 0.4.0
Summary: Data EDA & QC Package with Python
Home-page: https://github.com/Leejung8763/NexR_dqc
Author: Lee Jung
Author-email: leejung8763@naver.com
License: MIT
Download-URL: https://github.com/Leejung8763/NexR_dqc/archive/refs/tags/0.4.0.tar.gz
Keywords: pypi
Platform: UNKNOWN
Classifier: License :: OSI Approved :: MIT License
Classifier: Programming Language :: Python :: 3.7
Classifier: Programming Language :: Python :: 3.8
Classifier: Programming Language :: Python :: 3.9
Requires-Python: >=3
Requires-Dist: numpy
Requires-Dist: pandas (==1.2.4)
Requires-Dist: pyarrow
Requires-Dist: openpyxl
Requires-Dist: xlsxwriter
